tablib/__init__.py
tablib/_version.py
tablib/core.py
tablib/exceptions.py
tablib/utils.py
tablib/_vendor/__init__.py
tablib/_vendor/dbfpy/__init__.py
tablib/_vendor/dbfpy/dbf.py
tablib/_vendor/dbfpy/dbfnew.py
tablib/_vendor/dbfpy/fields.py
tablib/_vendor/dbfpy/header.py
tablib/_vendor/dbfpy/record.py
tablib/_vendor/dbfpy/utils.py
tablib/formats/__init__.py
tablib/formats/_cli.py
tablib/formats/_csv.py
tablib/formats/_dbf.py
tablib/formats/_df.py
tablib/formats/_html.py
tablib/formats/_jira.py
tablib/formats/_json.py
tablib/formats/_latex.py
tablib/formats/_ods.py
tablib/formats/_rst.py
tablib/formats/_tsv.py
tablib/formats/_xls.py
tablib/formats/_xlsx.py
tablib/formats/_yaml.py
tablib-3.7.0.dist-info/AUTHORS
tablib-3.7.0.dist-info/LICENSE
tablib-3.7.0.dist-info/METADATA
tablib-3.7.0.dist-info/WHEEL
tablib-3.7.0.dist-info/top_level.txt
tablib-3.7.0.dist-info/RECORD
