Metadata-Version: 2.1
Name: tablib
Version: 3.7.0
Summary: Format agnostic tabular data library (XLS, JSON, YAML, CSV, etc.)
Author-email: Kenneth Reitz <me@kennethreitz.org>
Maintainer: Hugo van Kemenade
Maintainer-email: Jazzband Team <roadies@jazzband.co>, Claude Paroz <claude@2xlibre.net>
License: MIT License
Project-URL: homepage, https://tablib.readthedocs.io
Project-URL: documentation, https://tablib.readthedocs.io
Project-URL: repository, https://github.com/jazzband/tablib
Project-URL: changelog, https://github.com/jazzband/tablib/blob/master/HISTORY.md
Classifier: Development Status :: 5 - Production/Stable
Classifier: Intended Audience :: Developers
Classifier: Natural Language :: English
Classifier: License :: OSI Approved :: MIT License
Classifier: Programming Language :: Python
Classifier: Programming Language :: Python :: 3 :: Only
Classifier: Programming Language :: Python :: 3
Classifier: Programming Language :: Python :: 3.9
Classifier: Programming Language :: Python :: 3.10
Classifier: Programming Language :: Python :: 3.11
Classifier: Programming Language :: Python :: 3.12
Classifier: Programming Language :: Python :: 3.13
Requires-Python: >=3.9
License-File: LICENSE
License-File: AUTHORS
Provides-Extra: all
Requires-Dist: odfpy; extra == "all"
Requires-Dist: openpyxl>=2.6.0; extra == "all"
Requires-Dist: pandas; extra == "all"
Requires-Dist: pyyaml; extra == "all"
Requires-Dist: tabulate; extra == "all"
Requires-Dist: xlrd; extra == "all"
Requires-Dist: xlwt; extra == "all"
Provides-Extra: cli
Requires-Dist: tabulate; extra == "cli"
Provides-Extra: html
Provides-Extra: ods
Requires-Dist: odfpy; extra == "ods"
Provides-Extra: pandas
Requires-Dist: pandas; extra == "pandas"
Provides-Extra: xls
Requires-Dist: xlrd; extra == "xls"
Requires-Dist: xlwt; extra == "xls"
Provides-Extra: xlsx
Requires-Dist: openpyxl>=2.6.0; extra == "xlsx"
Provides-Extra: yaml
Requires-Dist: pyyaml; extra == "yaml"
